seiton_printer/__init__.py
seiton_printer/commands.py
seiton_printer/seiton.py
seiton_printer-1.0.3.dist-info/METADATA
seiton_printer-1.0.3.dist-info/WHEEL
seiton_printer-1.0.3.dist-info/top_level.txt
seiton_printer-1.0.3.dist-info/RECORD
