Metadata-Version: 2.1
Name: seiton-printer
Version: 1.0.3
Summary: Set de metodos para controlar la impresora Seiton
Home-page: https://github.com/ernes128/seiton-driver-python
Author: Mauro
Author-email: seiton@eklabs.dev
License: UNKNOWN
Platform: UNKNOWN
Requires-Python: >=3.6
Requires-Dist: Pillow
